LICENSE
MANIFEST.in
README
setup.py
django_trails.egg-info/PKG-INFO
django_trails.egg-info/SOURCES.txt
django_trails.egg-info/dependency_links.txt
django_trails.egg-info/not-zip-safe
django_trails.egg-info/requires.txt
django_trails.egg-info/top_level.txt
trails/__init__.py
trails/admin.py
trails/api.py
trails/managers.py
trails/middleware.py
trails/models.py
trails/modelstate.py
trails/settings.py
trails/signals.py
trails/tests.py
trails/utils.py
trails/migrations/0001_initial.py
trails/migrations/__init__.py
trails/templates/admin/trails_history.html
trails/templates/trails/_default.txt