Metadata-Version: 1.0
Name: django-trails
Version: 0.2a2
Summary: Django app for audit logging.
Home-page: https://projects.ninemoreminutes.com/projects/django-trails/
Author: Nine More Minutes, Inc.
Author-email: support@ninemoreminutes.com
License: BSD
Keywords: django audit trail logging
Platform: UNKNOWN
Classifier: Development Status :: 3 - Alpha
Classifier: Environment :: Web Environment
Classifier: Framework :: Django
Classifier: Intended Audience :: Developers
Classifier: License :: OSI Approved :: BSD License
Classifier: Operating System :: OS Independent
Classifier: Programming Language :: Python
Classifier: Topic :: Internet :: WWW/HTTP
Classifier: Topic :: Software Development :: Libraries
